{"id": 4729, "qid": 4729, "publicid": 4729, "orgid": 0, "levelname": "2D+", "min_levelname": "1D", "max_levelname": "5D", "qtype": 2, "qtypename": "\u624b\u7b4b\u9898", "status": 2, "userid": 1, "username": "admin", "hasdia": true, "dias": [], "attr_type": 0, "layoutnumber": 1, "issingle": true, "enable_answer": true, "sms_count": 3, "edit_count": 3, "islei": false, "leiid": 0, "taotaiid": 0, "bookinfos": [{"bookname": "\u300a\u65e5\u672c\u68cb\u9662-\u624b\u7b4b\u5927\u4e8b\u5178\u300b", "bookid": 469, "pinyin": "", "nodename": "\u7b2c\u4e94\u7ae0", "bookurl": 469}], "specs": [], "taskresult": {"ok_nums": [0, 0, 0, 1, 12, 0, 1, 0, 1, 1, 1, 1, 2, 2, 2, 4, 6, 10, 6, 12, 13, 15, 8, 6, 6, 6, 8, 7, 5, 6], "fail_nums": [0, 2, 0, 0, 32, 0, 1, 4, 1, 3, 2, 7, 5, 8, 6, 11, 11, 17, 9, 10, 5, 7, 4, 6, 6, 4, 7, 0, 2, 4], "ok_total": 142, "fail_total": 174}, "xuandians": [], "xds": [], "options": [], "vote": 4.7, "name": "", "title": "", "c": "amsTUUMQHRATVkMQHRATV0IQbBwRaRBXQBIdEhBVQBIdEhBRQRIdEhBWQRJsbw==", "r": 1, "prepos": [["qc", "qd", "pe"], ["qe", "qg", "pc"]], "xv": 10, "points": [], "lu": 19, "blackfirst": true, "is_share": true, "answers": [{"id": 2909128, "st": 2, "ty": 1, "nu": 37, "username": "kenny", "userid": 23199, "pts": [{"p": "pb", "c": ""}, {"p": "oe", "c": ""}, {"p": "pf", "c": ""}, {"p": "qf", "c": ""}, {"p": "ob", "c": ""}], "v": 0, "ok_count": 50, "change_count": 0, "bad_count": 0, "error_count": 0, "created": 1760985836}, {"id": 488886, "st": 1, "ty": 1, "nu": 24, "username": "\u59dc\u4e00\u535a", "userid": 30474, "pts": [{"p": "pb", "c": ""}, {"p": "oe", "c": ""}, {"p": "pf", "c": ""}, {"p": "qf", "c": ""}, {"p": "nc", "c": ""}, {"p": "od", "c": ""}, {"p": "ob", "c": ""}, {"p": "og", "c": ""}], "v": 0, "ok_count": 1, "change_count": 0, "bad_count": 0, "error_count": 1, "created": 1491911137}, {"id": 489009, "st": 2, "ty": 1, "nu": 25, "username": "\u674e\u4e4b\u7136", "userid": 50204, "pts": [{"p": "pb", "c": ""}, {"p": "oe", "c": ""}, {"p": "pf", "c": ""}, {"p": "qf", "c": ""}, {"p": "nc", "c": ""}], "v": 0, "ok_count": 13, "change_count": 0, "bad_count": 0, "error_count": 0, "created": 1491991768}, {"id": 834040, "st": 1, "ty": 1, "nu": 27, "username": "w_22194622193728", "userid": 475495, "pts": [{"p": "pb", "c": ""}, {"p": "oe", "c": ""}, {"p": "pf", "c": ""}, {"p": "qf", "c": ""}, {"p": "nc", "c": ""}, {"p": "og", "c": ""}, {"p": "od", "c": ""}, {"p": "of", "c": ""}, {"p": "oc", "c": ""}], "v": 0, "ok_count": 1, "change_count": 0, "bad_count": 0, "error_count": 0, "created": 1563937497}, {"id": 1033588, "st": 1, "ty": 1, "nu": 28, "username": "\u6bd5\u65af\u6db5", "userid": 332100, "pts": [{"p": "pb", "c": ""}, {"p": "ob", "c": ""}, {"p": "qf", "c": ""}, {"p": "re", "c": ""}, {"p": "rf", "c": ""}, {"p": "pf", "c": ""}, {"p": "oe", "c": ""}], "v": 0, "ok_count": 1, "change_count": 1, "bad_count": 0, "error_count": 0, "created": 1583073570}, {"id": 1104679, "st": 1, "ty": 1, "nu": 29, "username": "w_3219953819139", "userid": 488036, "pts": [{"p": "pb", "c": ""}, {"p": "oe", "c": ""}, {"p": "pf", "c": ""}, {"p": "re", "c": ""}, {"p": "nc", "c": ""}, {"p": "od", "c": ""}, {"p": "rb", "c": ""}, {"p": "og", "c": ""}], "v": 0, "ok_count": 1, "change_count": 0, "bad_count": 0, "error_count": 0, "created": 1587554888}, {"id": 1393174, "st": 1, "ty": 1, "nu": 31, "username": "\u65b9\u5341\u8776", "userid": 15487, "pts": [{"p": "pb", "c": ""}, {"p": "oe", "c": ""}, {"p": "pf", "c": ""}, {"p": "re", "c": ""}, {"p": "ob", "c": ""}, {"p": "nc", "c": ""}, {"p": "mc", "c": ""}, {"p": "nd", "c": ""}, {"p": "oc", "c": ""}, {"p": "od", "c": ""}, {"p": "nb", "c": ""}, {"p": "qb", "c": ""}, {"p": "rb", "c": ""}, {"p": "rc", "c": ""}, {"p": "qa", "c": ""}, {"p": "rd", "c": ""}, {"p": "qb", "c": ""}, {"p": "md", "c": ""}, {"p": "ld", "c": ""}], "v": 0, "ok_count": 1, "change_count": 0, "bad_count": 0, "error_count": 0, "created": 1616047532}, {"id": 1832277, "st": 1, "ty": 1, "nu": 32, "username": "\u8d3a\u8000013", "userid": 1268923, "pts": [{"p": "pb", "c": ""}, {"p": "oe", "c": ""}, {"p": "pf", "c": ""}, {"p": "qf", "c": ""}, {"p": "nc", "c": ""}, {"p": "of", "c": ""}], "v": 0, "ok_count": 1, "change_count": 0, "bad_count": 0, "error_count": 0, "created": 1659361112}, {"id": 1848096, "st": 1, "ty": 1, "nu": 33, "username": "goalextang", "userid": 996300, "pts": [{"p": "pb", "c": ""}, {"p": "oe", "c": ""}, {"p": "pf", "c": ""}, {"p": "qf", "c": ""}, {"p": "ob", "c": ""}, {"p": "og", "c": ""}, {"p": "od", "c": ""}, {"p": "pg", "c": ""}, {"p": "oc", "c": ""}, {"p": "of", "c": ""}, {"p": "pd", "c": ""}], "v": 0, "ok_count": 1, "change_count": 0, "bad_count": 0, "error_count": 0, "created": 1660659723}, {"id": 2156837, "st": 1, "ty": 1, "nu": 35, "username": "wx_377658419023", "userid": 1647141, "pts": [{"p": "pb", "c": ""}, {"p": "oe", "c": ""}, {"p": "pf", "c": ""}, {"p": "qf", "c": ""}, {"p": "ob", "c": ""}, {"p": "nc", "c": ""}, {"p": "mc", "c": ""}, {"p": "nd", "c": ""}, {"p": "oc", "c": ""}, {"p": "od", "c": ""}, {"p": "nb", "c": ""}, {"p": "md", "c": ""}, {"p": "lc", "c": ""}, {"p": "pg", "c": ""}], "v": 0, "ok_count": 1, "change_count": 0, "bad_count": 0, "error_count": 0, "created": 1691286707}, {"id": 2741863, "st": 1, "ty": 1, "nu": 36, "username": "wx_336002119196", "userid": 889001, "pts": [{"p": "pb", "c": ""}, {"p": "ob", "c": ""}, {"p": "oc", "c": ""}, {"p": "od", "c": ""}, {"p": "oe", "c": ""}, {"p": "nc", "c": ""}, {"p": "qf", "c": ""}, {"p": "re", "c": ""}, {"p": "rf", "c": ""}, {"p": "qb", "c": ""}, {"p": "rb", "c": ""}, {"p": "pa", "c": ""}, {"p": "pg", "c": ""}], "v": 0, "ok_count": 1, "change_count": 0, "bad_count": 0, "error_count": 0, "created": 1752454176}, {"id": 407275, "st": 2, "ty": 2, "nu": 23, "username": "john77", "userid": 24146, "pts": [{"p": "pb", "c": ""}, {"p": "ob", "c": ""}, {"p": "qf", "c": ""}, {"p": "re", "c": ""}, {"p": "rf", "c": ""}, {"p": "pf", "c": ""}, {"p": "oe", "c": ""}, {"p": "rg", "c": ""}, {"p": "oc", "c": ""}], "v": 0, "ok_count": 3, "change_count": 51, "bad_count": 0, "error_count": 0, "created": 1469862530}, {"id": 2909130, "st": 2, "ty": 2, "nu": 38, "username": "kenny", "userid": 23199, "pts": [{"p": "pb", "c": ""}, {"p": "oe", "c": ""}, {"p": "pf", "c": ""}, {"p": "re", "c": ""}, {"p": "ob", "c": ""}], "v": 0, "ok_count": 0, "change_count": 50, "bad_count": 0, "error_count": 0, "created": 1760985924}, {"id": 2909131, "st": 2, "ty": 2, "nu": 39, "username": "kenny", "userid": 23199, "pts": [{"p": "pb", "c": ""}, {"p": "oe", "c": ""}, {"p": "pf", "c": ""}, {"p": "re", "c": ""}, {"p": "nc", "c": ""}], "v": 0, "ok_count": 0, "change_count": 50, "bad_count": 0, "error_count": 0, "created": 1760985927}, {"id": 1393173, "st": 1, "ty": 2, "nu": 30, "username": "\u65b9\u5341\u8776", "userid": 15487, "pts": [{"p": "pb", "c": ""}, {"p": "ob", "c": ""}, {"p": "qf", "c": ""}, {"p": "re", "c": ""}, {"p": "rf", "c": ""}, {"p": "pf", "c": ""}, {"p": "oe", "c": ""}, {"p": "rg", "c": ""}, {"p": "oc", "c": ""}, {"p": "of", "c": ""}], "v": 0, "ok_count": 0, "change_count": 1, "bad_count": 0, "error_count": 0, "created": 1616047363}, {"id": 2156836, "st": 1, "ty": 2, "nu": 34, "username": "wx_377658419023", "userid": 1647141, "pts": [{"p": "pb", "c": ""}, {"p": "oe", "c": ""}, {"p": "pf", "c": ""}, {"p": "qf", "c": ""}, {"p": "ob", "c": ""}, {"p": "nc", "c": ""}, {"p": "mc", "c": ""}, {"p": "nb", "c": ""}, {"p": "oc", "c": ""}, {"p": "od", "c": ""}, {"p": "nd", "c": ""}], "v": 0, "ok_count": 0, "change_count": 1, "bad_count": 0, "error_count": 0, "created": 1691286692}, {"id": 15564, "st": 2, "ty": 3, "nu": 11, "username": "admin", "userid": 1, "pts": [{"p": "re", "c": ""}, {"p": "qf", "c": ""}, {"p": "pb", "c": ""}, {"p": "ob", "c": ""}, {"p": "qb", "c": ""}, {"p": "nc", "c": ""}], "v": 0, "ok_count": 0, "change_count": 0, "bad_count": 0, "error_count": 0, "created": 0}, {"id": 15565, "st": 2, "ty": 3, "nu": 12, "username": "admin", "userid": 1, "pts": [{"p": "re", "c": ""}, {"p": "qf", "c": ""}, {"p": "oe", "c": ""}, {"p": "qb", "c": ""}, {"p": "rb", "c": ""}, {"p": "pb", "c": ""}], "v": 0, "ok_count": 0, "change_count": 0, "bad_count": 0, "error_count": 0, "created": 0}, {"id": 2909133, "st": 2, "ty": 3, "nu": 40, "username": "kenny", "userid": 23199, "pts": [{"p": "oe", "c": ""}, {"p": "qb", "c": ""}, {"p": "qf", "c": ""}, {"p": "re", "c": ""}, {"p": "rf", "c": ""}, {"p": "rc", "c": ""}], "v": 0, "ok_count": 0, "change_count": 0, "bad_count": 50, "error_count": 0, "created": 1760985963}, {"id": 495864, "st": 1, "ty": 3, "nu": 26, "username": "qingdaotomy", "userid": 13972, "pts": [{"p": "pb", "c": ""}, {"p": "oe", "c": ""}, {"p": "pf", "c": ""}, {"p": "qf", "c": ""}, {"p": "ob", "c": ""}, {"p": "nc", "c": ""}], "v": 0, "ok_count": 0, "change_count": 1, "bad_count": 1, "error_count": 0, "created": 1494658407}], "ans_count": 20, "andata": {"0": {"subs": [1, 18, 28], "p": 0, "id": 0, "aids": [], "pt": "", "o": 0, "c": 0, "f": 0, "u": 0, "tip": ""}, "1": {"subs": [2, 7], "p": 0, "id": 1, "aids": [2909128, 489009, 407275, 2909130, 2909131], "pt": "pb", "o": 1, "c": 1, "f": 0, "u": 0, "tip": ""}, "2": {"subs": [3], "p": 1, "id": 2, "aids": [2909128, 489009, 2909130, 2909131], "pt": "oe", "o": 1, "c": 1, "f": 0, "u": 0, "tip": ""}, "3": {"subs": [4, 15], "p": 2, "id": 3, "aids": [2909128, 489009, 2909130, 2909131], "pt": "pf", "o": 1, "c": 1, "f": 0, "u": 0, "tip": ""}, "4": {"subs": [5, 6], "p": 3, "id": 4, "aids": [2909128, 489009], "pt": "qf", "o": 1, "c": 0, "f": 0, "u": 0, "tip": ""}, "5": {"subs": [], "p": 4, "id": 5, "aids": [2909128], "pt": "ob", "o": 1, "c": 0, "f": 0, "u": 0, "tip": ""}, "6": {"subs": [], "p": 4, "id": 6, "aids": [489009], "pt": "nc", "o": 1, "c": 0, "f": 0, "u": 0, "tip": ""}, "7": {"subs": [8], "p": 1, "id": 7, "aids": [407275], "pt": "ob", "o": 0, "c": 1, "f": 0, "u": 0, "tip": ""}, "8": {"subs": [9], "p": 7, "id": 8, "aids": [407275], "pt": "qf", "o": 0, "c": 1, "f": 0, "u": 0, "tip": ""}, "9": {"subs": [10], "p": 8, "id": 9, "aids": [407275], "pt": "re", "o": 0, "c": 1, "f": 0, "u": 0, "tip": ""}, "10": {"subs": [11], "p": 9, "id": 10, "aids": [407275], "pt": "rf", "o": 0, "c": 1, "f": 0, "u": 0, "tip": ""}, "11": {"subs": [12], "p": 10, "id": 11, "aids": [407275], "pt": "pf", "o": 0, "c": 1, "f": 0, "u": 0, "tip": ""}, "12": {"subs": [13], "p": 11, "id": 12, "aids": [407275], "pt": "oe", "o": 0, "c": 1, "f": 0, "u": 0, "tip": ""}, "13": {"subs": [14], "p": 12, "id": 13, "aids": [407275], "pt": "rg", "o": 0, "c": 1, "f": 0, "u": 0, "tip": ""}, "14": {"subs": [], "p": 13, "id": 14, "aids": [407275], "pt": "oc", "o": 0, "c": 1, "f": 0, "u": 0, "tip": ""}, "15": {"subs": [16, 17], "p": 3, "id": 15, "aids": [2909130, 2909131], "pt": "re", "o": 0, "c": 1, "f": 0, "u": 0, "tip": ""}, "16": {"subs": [], "p": 15, "id": 16, "aids": [2909130], "pt": "ob", "o": 0, "c": 1, "f": 0, "u": 0, "tip": ""}, "17": {"subs": [], "p": 15, "id": 17, "aids": [2909131], "pt": "nc", "o": 0, "c": 1, "f": 0, "u": 0, "tip": ""}, "18": {"subs": [19], "p": 0, "id": 18, "aids": [15564, 15565], "pt": "re", "o": 0, "c": 0, "f": 1, "u": 0, "tip": ""}, "19": {"subs": [20, 24], "p": 18, "id": 19, "aids": [15564, 15565], "pt": "qf", "o": 0, "c": 0, "f": 1, "u": 0, "tip": ""}, "20": {"subs": [21], "p": 19, "id": 20, "aids": [15564], "pt": "pb", "o": 0, "c": 0, "f": 1, "u": 0, "tip": ""}, "21": {"subs": [22], "p": 20, "id": 21, "aids": [15564], "pt": "ob", "o": 0, "c": 0, "f": 1, "u": 0, "tip": ""}, "22": {"subs": [23], "p": 21, "id": 22, "aids": [15564], "pt": "qb", "o": 0, "c": 0, "f": 1, "u": 0, "tip": ""}, "23": {"subs": [], "p": 22, "id": 23, "aids": [15564], "pt": "nc", "o": 0, "c": 0, "f": 1, "u": 0, "tip": ""}, "24": {"subs": [25], "p": 19, "id": 24, "aids": [15565], "pt": "oe", "o": 0, "c": 0, "f": 1, "u": 0, "tip": ""}, "25": {"subs": [26], "p": 24, "id": 25, "aids": [15565], "pt": "qb", "o": 0, "c": 0, "f": 1, "u": 0, "tip": ""}, "26": {"subs": [27], "p": 25, "id": 26, "aids": [15565], "pt": "rb", "o": 0, "c": 0, "f": 1, "u": 0, "tip": ""}, "27": {"subs": [], "p": 26, "id": 27, "aids": [15565], "pt": "pb", "o": 0, "c": 0, "f": 1, "u": 0, "tip": ""}, "28": {"subs": [29], "p": 0, "id": 28, "aids": [2909133], "pt": "oe", "o": 0, "c": 0, "f": 1, "u": 0, "tip": ""}, "29": {"subs": [30], "p": 28, "id": 29, "aids": [2909133], "pt": "qb", "o": 0, "c": 0, "f": 1, "u": 0, "tip": ""}, "30": {"subs": [31], "p": 29, "id": 30, "aids": [2909133], "pt": "qf", "o": 0, "c": 0, "f": 1, "u": 0, "tip": ""}, "31": {"subs": [32], "p": 30, "id": 31, "aids": [2909133], "pt": "re", "o": 0, "c": 0, "f": 1, "u": 0, "tip": ""}, "32": {"subs": [33], "p": 31, "id": 32, "aids": [2909133], "pt": "rf", "o": 0, "c": 0, "f": 1, "u": 0, "tip": ""}, "33": {"subs": [], "p": 32, "id": 33, "aids": [2909133], "pt": "rc", "o": 0, "c": 0, "f": 1, "u": 0, "tip": ""}}, "disuse": 20, "sx": 11, "sy": 10, "pos_x1": 8, "pos_x2": 18, "pos_y1": 0, "pos_y2": 9, "ineb": false, "extendwidth": 1, "signs": [], "luozis": [], "isguess": false, "objtype": "timu", "ru": 1, "content": "amsTQ1YQHRATQ1EQHRATQlcQbBwRaRBCVRIdEhBDVhIdEhBDVBIdEhBCUhJsbw==", "ok_answers": "amsTQlAQHRATXVcQHRATQlQQHRATQ1QQHRATXVAQbBwRaRBCUxIdEhBdVBIdEhBCVxIdEhBDVxIdEhBcUhJsbw==", "change_answers": "amsTQlAQHRATXVAQHRATQ1QQHRATQFcQHRATQFQQHRATQlQQHRATXVcQHRATQFUQHRATXVEQbBwRaRBCUxIdEhBdVBIdEhBCVxIdEhBAVBIdEhBdUxJsHhJpE0BTEB4SE19UEB4SE0BXEB4SE0JUEB4SE15SEG9v", "fail_answers": "amsTQFcQHRATQ1QQHRATQlAQHRATXVAQHRATQ1AQHRATXFEQbBwRaRBAVBIdEhBDVxIdEhBdVBIdEhBDUxIdEhBAUxIdEhBCUxJsHhJpE19UEB4SE0FTEB4SE0FXEB4SE0JUEB4SE0JXEB4SE0JSEG9v", "level": 391, "desc": "", "yes_count": 142, "no_count": 174, "pos": [], "attrtype": 0, "showrettip": false, "is_public": true, "inerror": false, "qshids": [], "myan": null, "hasbook": false, "hasspec": false, "myoper": {"mystar": false, "mytags": [], "tags": []}, "candisuseall": false, "userlevel": 0, "clicktime": 0, "xz": 0, "comments": []}
