{"hasdia": true, "username": "\u7231\u4e50\u5955", "pos_y1": 0, "pos_y2": 7, "islei": false, "myoper": {"mystar": false, "tags": [], "mytags": []}, "signs": [], "taotaiid": 0, "qshids": [], "hasbook": false, "orgid": 0, "disuse": 3, "vote": 5.0, "qtype": 1, "id": 32403, "points": [], "publicid": 32403, "title": "\u6865\u672c\u5b87\u592a\u90ce\u4e5d\u6bb5\u521b\u4f5c", "ineb": false, "xv": 8, "comments": [{"username": "\u5b59\u5fc6\u679c", "showcontent": "\u2026\u2026", "douname": "", "headpath": "headicon_128.png", "userid": 261310, "updated": 1585053082, "doustatus": 0, "id": 622206, "dou": 0}, {"username": "\u90b5\u4fca\u535a", "showcontent": "\u8fd9\u9898\u67092D\uff1f", "douname": "", "headpath": "head/2020/2/12/268632_97805_59_25.png", "userid": 268632, "updated": 1590992070, "doustatus": 0, "id": 779241, "dou": 0}, {"username": "xuyicheng", "showcontent": "1D\u624d\u53ef\u4ee5", "douname": "", "headpath": "headicon_128.png", "userid": 142250, "updated": 1622200956, "doustatus": 0, "id": 1031904, "dou": 0}, {"username": "\u9648\u5e7c\u5b89", "showcontent": "nan  bu  nan", "douname": "", "headpath": "headicon_128.png", "userid": 668731, "updated": 1702470326, "doustatus": 0, "id": 1682553, "dou": 0}], "specs": [], "options": [], "max_levelname": "", "hasspec": false, "blackfirst": true, "luozis": [], "dias": [], "status": 2, "pos_x2": 18, "pos_x1": 11, "andata": {"0": {"c": 0, "subs": [1, 17, 23, 29], "pt": "", "f": 0, "tip": "", "o": 0, "p": 0, "u": 0, "aids": [], "id": 0}, "1": {"c": 1, "subs": [2], "pt": "qc", "f": 1, "tip": "", "o": 1, "p": 0, "u": 0, "aids": [282233, 159851, 372566, 1043866, 1043867], "id": 1}, "2": {"c": 1, "subs": [3, 8, 38], "pt": "rc", "f": 1, "tip": "", "o": 1, "p": 1, "u": 0, "aids": [282233, 159851, 372566, 1043866, 1043867], "id": 2}, "3": {"c": 1, "subs": [4, 13], "pt": "pb", "f": 0, "tip": "", "o": 1, "p": 2, "u": 0, "aids": [282233, 372566], "id": 3}, "4": {"c": 0, "subs": [5], "pt": "pa", "f": 0, "tip": "", "o": 1, "p": 3, "u": 0, "aids": [282233], "id": 4}, "5": {"c": 0, "subs": [6], "pt": "rd", "f": 0, "tip": "", "o": 1, "p": 4, "u": 0, "aids": [282233], "id": 5}, "6": {"c": 0, "subs": [7], "pt": "sd", "f": 0, "tip": "", "o": 1, "p": 5, "u": 0, "aids": [282233], "id": 6}, "7": {"c": 0, "subs": [], "pt": "qd", "f": 0, "tip": "", "o": 1, "p": 6, "u": 0, "aids": [282233], "id": 7}, "8": {"c": 0, "subs": [9], "pt": "rd", "f": 1, "tip": "", "o": 1, "p": 2, "u": 0, "aids": [159851, 1043867], "id": 8}, "9": {"c": 0, "subs": [10, 42], "pt": "sd", "f": 1, "tip": "", "o": 1, "p": 8, "u": 0, "aids": [159851, 1043867], "id": 9}, "10": {"c": 0, "subs": [11], "pt": "pb", "f": 0, "tip": "", "o": 1, "p": 9, "u": 0, "aids": [159851], "id": 10}, "11": {"c": 0, "subs": [12], "pt": "pa", "f": 0, "tip": "", "o": 1, "p": 10, "u": 0, "aids": [159851], "id": 11}, "12": {"c": 0, "subs": [], "pt": "qd", "f": 0, "tip": "", "o": 1, "p": 11, "u": 0, "aids": [159851], "id": 12}, "13": {"c": 1, "subs": [14], "pt": "pc", "f": 0, "tip": "", "o": 0, "p": 3, "u": 0, "aids": [372566], "id": 13}, "14": {"c": 1, "subs": [15], "pt": "qb", "f": 0, "tip": "", "o": 0, "p": 13, "u": 0, "aids": [372566], "id": 14}, "15": {"c": 1, "subs": [16], "pt": "pa", "f": 0, "tip": "", "o": 0, "p": 14, "u": 0, "aids": [372566], "id": 15}, "16": {"c": 1, "subs": [], "pt": "rd", "f": 0, "tip": "", "o": 0, "p": 15, "u": 0, "aids": [372566], "id": 16}, "17": {"c": 0, "subs": [18], "pt": "rc", "f": 1, "tip": "", "o": 0, "p": 0, "u": 0, "aids": [1152249], "id": 17}, "18": {"c": 0, "subs": [19], "pt": "qb", "f": 1, "tip": "", "o": 0, "p": 17, "u": 0, "aids": [1152249], "id": 18}, "19": {"c": 0, "subs": [20], "pt": "qc", "f": 1, "tip": "", "o": 0, "p": 18, "u": 0, "aids": [1152249], "id": 19}, "20": {"c": 0, "subs": [21], "pt": "pb", "f": 1, "tip": "", "o": 0, "p": 19, "u": 0, "aids": [1152249], "id": 20}, "21": {"c": 0, "subs": [22], "pt": "sd", "f": 1, "tip": "", "o": 0, "p": 20, "u": 0, "aids": [1152249], "id": 21}, "22": {"c": 0, "subs": [], "pt": "rd", "f": 1, "tip": "", "o": 0, "p": 21, "u": 0, "aids": [1152249], "id": 22}, "23": {"c": 0, "subs": [24], "pt": "qb", "f": 1, "tip": "", "o": 0, "p": 0, "u": 0, "aids": [746431], "id": 23}, "24": {"c": 0, "subs": [25], "pt": "rc", "f": 1, "tip": "", "o": 0, "p": 23, "u": 0, "aids": [746431], "id": 24}, "25": {"c": 0, "subs": [26], "pt": "qc", "f": 1, "tip": "", "o": 0, "p": 24, "u": 0, "aids": [746431], "id": 25}, "26": {"c": 0, "subs": [27], "pt": "rd", "f": 1, "tip": "", "o": 0, "p": 25, "u": 0, "aids": [746431], "id": 26}, "27": {"c": 0, "subs": [28], "pt": "pa", "f": 1, "tip": "", "o": 0, "p": 26, "u": 0, "aids": [746431], "id": 27}, "28": {"c": 0, "subs": [], "pt": "pb", "f": 1, "tip": "", "o": 0, "p": 27, "u": 0, "aids": [746431], "id": 28}, "29": {"c": 0, "subs": [30], "pt": "rd", "f": 1, "tip": "", "o": 0, "p": 0, "u": 0, "aids": [708218], "id": 29}, "30": {"c": 0, "subs": [31], "pt": "qc", "f": 1, "tip": "", "o": 0, "p": 29, "u": 0, "aids": [708218], "id": 30}, "31": {"c": 0, "subs": [32], "pt": "rc", "f": 1, "tip": "", "o": 0, "p": 30, "u": 0, "aids": [708218], "id": 31}, "32": {"c": 0, "subs": [33], "pt": "qb", "f": 1, "tip": "", "o": 0, "p": 31, "u": 0, "aids": [708218], "id": 32}, "33": {"c": 0, "subs": [34], "pt": "pb", "f": 1, "tip": "", "o": 0, "p": 32, "u": 0, "aids": [708218], "id": 33}, "34": {"c": 0, "subs": [35], "pt": "sd", "f": 1, "tip": "", "o": 0, "p": 33, "u": 0, "aids": [708218], "id": 34}, "35": {"c": 0, "subs": [36], "pt": "pc", "f": 1, "tip": "", "o": 0, "p": 34, "u": 0, "aids": [708218], "id": 35}, "36": {"c": 0, "subs": [37], "pt": "pa", "f": 1, "tip": "", "o": 0, "p": 35, "u": 0, "aids": [708218], "id": 36}, "37": {"c": 0, "subs": [], "pt": "pb", "f": 1, "tip": "", "o": 0, "p": 36, "u": 0, "aids": [708218], "id": 37}, "38": {"c": 0, "subs": [39], "pt": "qb", "f": 1, "tip": "", "o": 0, "p": 2, "u": 0, "aids": [1043866], "id": 38}, "39": {"c": 0, "subs": [40], "pt": "rd", "f": 1, "tip": "", "o": 0, "p": 38, "u": 0, "aids": [1043866], "id": 39}, "40": {"c": 0, "subs": [41], "pt": "pa", "f": 1, "tip": "", "o": 0, "p": 39, "u": 0, "aids": [1043866], "id": 40}, "41": {"c": 0, "subs": [], "pt": "pb", "f": 1, "tip": "", "o": 0, "p": 40, "u": 0, "aids": [1043866], "id": 41}, "42": {"c": 0, "subs": [43], "pt": "qb", "f": 1, "tip": "", "o": 0, "p": 9, "u": 0, "aids": [1043867], "id": 42}, "43": {"c": 0, "subs": [44], "pt": "qd", "f": 1, "tip": "", "o": 0, "p": 42, "u": 0, "aids": [1043867], "id": 43}, "44": {"c": 0, "subs": [45], "pt": "pa", "f": 1, "tip": "", "o": 0, "p": 43, "u": 0, "aids": [1043867], "id": 44}, "45": {"c": 0, "subs": [46], "pt": "pb", "f": 1, "tip": "", "o": 0, "p": 44, "u": 0, "aids": [1043867], "id": 45}, "46": {"c": 0, "subs": [47], "pt": "pc", "f": 1, "tip": "", "o": 0, "p": 45, "u": 0, "aids": [1043867], "id": 46}, "47": {"c": 0, "subs": [], "pt": "qa", "f": 1, "tip": "", "o": 0, "p": 46, "u": 0, "aids": [1043867], "id": 47}}, "is_public": true, "userlevel": -100, "c": "amsTUkERHRATUl0RHRATUV0RHRATUF0RHRATV10RHRATVlwRHRATVV0RHRATVUMRHRATVUIRHRATVUERHRATVUARHRATUUARHRATUUERbBwRaBFQQhIdExFWQhIdExFWQxIdExFWQBIdExFWQRIdExFXQRIdExFXXhIdExFQXhIdExFRXhIdExFSXhIdExFSQBJsbg==", "answers": [{"username": "\u5357\u5bab\u7cef\u7389\u7c73", "change_count": 0, "ty": 1, "userid": 15842, "id": 282233, "ok_count": 26, "error_count": 0, "bad_count": 0, "v": 0, "st": 2, "pts": [{"p": "qc", "c": " "}, {"p": "rc", "c": " "}, {"p": "pb", "c": " "}, {"p": "pa", "c": " "}, {"p": "rd", "c": " "}, {"p": "sd", "c": " "}, {"p": "qd", "c": " "}], "nu": 2}, {"username": "\u7231\u4e50\u5955", "change_count": 0, "ty": 1, "userid": 2768, "id": 159851, "ok_count": 4, "error_count": 0, "bad_count": 0, "v": 0, "st": 2, "pts": [{"p": "qc", "c": ""}, {"p": "rc", "c": ""}, {"p": "rd", "c": ""}, {"p": "sd", "c": ""}, {"p": "pb", "c": ""}, {"p": "pa", "c": ""}, {"p": "qd", "c": ""}], "nu": 1}, {"username": "adtravis", "change_count": 0, "ty": 1, "userid": 1121102, "id": 2301494, "ok_count": 1, "error_count": 0, "bad_count": 0, "v": 0, "st": 1, "pts": [{"p": "qc", "c": ""}, {"p": "qb", "c": ""}, {"p": "rd", "c": ""}, {"p": "sd", "c": ""}, {"p": "pb", "c": ""}, {"p": "pa", "c": ""}, {"p": "pc", "c": ""}], "nu": 15}, {"username": "danch001", "change_count": 21, "ty": 2, "userid": 28231, "id": 372566, "ok_count": 1, "error_count": 0, "bad_count": 0, "v": 0, "st": 2, "pts": [{"p": "qc", "c": " "}, {"p": "rc", "c": " "}, {"p": "pb", "c": " "}, {"p": "pc", "c": " "}, {"p": "qb", "c": " "}, {"p": "pa", "c": " "}, {"p": "rd", "c": " "}], "nu": 3}, {"username": "\u6bd5\u65af\u6db5", "change_count": 0, "ty": 3, "userid": 332100, "id": 1152249, "ok_count": 0, "error_count": 0, "bad_count": 51, "v": 0, "st": 2, "pts": [{"p": "rc", "c": ""}, {"p": "qb", "c": ""}, {"p": "qc", "c": ""}, {"p": "pb", "c": ""}, {"p": "sd", "c": ""}, {"p": "rd", "c": ""}], "nu": 12}, {"username": "kenny", "change_count": 0, "ty": 3, "userid": 23199, "id": 746431, "ok_count": 0, "error_count": 0, "bad_count": 50, "v": 0, "st": 2, "pts": [{"p": "qb", "c": ""}, {"p": "rc", "c": ""}, {"p": "qc", "c": ""}, {"p": "rd", "c": ""}, {"p": "pa", "c": ""}, {"p": "pb", "c": ""}], "nu": 9}, {"username": "\u91d1\u9675\u68cb\u8bed\u8005", "change_count": 0, "ty": 3, "userid": 187305, "id": 708218, "ok_count": 0, "error_count": 0, "bad_count": 51, "v": 0, "st": 2, "pts": [{"p": "rd", "c": ""}, {"p": "qc", "c": ""}, {"p": "rc", "c": ""}, {"p": "qb", "c": ""}, {"p": "pb", "c": ""}, {"p": "sd", "c": ""}, {"p": "pc", "c": ""}, {"p": "pa", "c": ""}, {"p": "pb", "c": ""}], "nu": 8}, {"username": "kenny", "change_count": 0, "ty": 3, "userid": 23199, "id": 1043866, "ok_count": 0, "error_count": 0, "bad_count": 50, "v": 0, "st": 2, "pts": [{"p": "qc", "c": ""}, {"p": "rc", "c": ""}, {"p": "qb", "c": ""}, {"p": "rd", "c": ""}, {"p": "pa", "c": ""}, {"p": "pb", "c": ""}], "nu": 10}, {"username": "kenny", "change_count": 0, "ty": 3, "userid": 23199, "id": 1043867, "ok_count": 0, "error_count": 0, "bad_count": 50, "v": 0, "st": 2, "pts": [{"p": "qc", "c": ""}, {"p": "rc", "c": ""}, {"p": "rd", "c": ""}, {"p": "sd", "c": ""}, {"p": "qb", "c": ""}, {"p": "qd", "c": ""}, {"p": "pa", "c": ""}, {"p": "pb", "c": ""}, {"p": "pc", "c": ""}, {"p": "qa", "c": ""}], "nu": 11}, {"username": "\u91d1\u601d\u6e90", "change_count": 0, "ty": 3, "userid": 1142485, "id": 2043269, "ok_count": 0, "error_count": 0, "bad_count": 1, "v": 0, "st": 1, "pts": [{"p": "qc", "c": ""}, {"p": "qb", "c": ""}, {"p": "rd", "c": ""}, {"p": "sd", "c": ""}, {"p": "rc", "c": ""}, {"p": "pc", "c": ""}, {"p": "pb", "c": ""}, {"p": "pa", "c": ""}], "nu": 14}], "is_share": true, "lu": 19, "min_levelname": "", "candisuseall": false, "taskresult": {"ok_nums": [13, 14, 9, 11, 11, 8, 12, 21, 14, 8, 25, 30, 29, 88, 86, 271, 209, 226, 197, 202, 177, 98, 93, 81, 58, 73, 52, 38, 27, 36], "fail_total": 1733, "fail_nums": [34, 18, 29, 21, 14, 13, 27, 38, 33, 30, 51, 57, 78, 137, 151, 305, 174, 154, 115, 92, 58, 38, 12, 18, 13, 8, 7, 1, 1, 6], "ok_total": 2217}, "prepos": [["ra", "na", "nb", "nc", "nd"], ["sc", "se", "re"]], "sy": 8, "issingle": true, "xuandians": [], "sms_count": 1, "xz": 0, "edit_count": 1, "enable_answer": true, "name": "", "nexterrorurl": "", "ans_count": 10, "userid": 2768, "layoutnumber": 1, "sx": 8, "bookinfos": [{"pinyin": "", "bookname": "\u6865\u672c\u5b87\u592a\u90ce04\u8a70\u7881\u5c81\u65f6\u8bb0", "nodename": "365", "bookid": 28509, "bookurl": 28509}, {"pinyin": "sihuozhongji", "bookname": "\u6b7b\u6d3b\u8bad\u7ec3\u4e2d\u7ea7\u7bc7", "nodename": "\u6b7b\u6d3b", "bookid": 196, "bookurl": "sihuozhongji"}, {"pinyin": "", "bookname": "\u8a70\u68cb\u7687\u5e1d \u6865\u672c\u5b87\u592a\u90ce", "nodename": "\u5c81\u65f6\u8bb0", "bookid": 28499, "bookurl": 28499}, {"pinyin": "qiantian", "bookname": "\u8bd8\u68cb\u540d\u5bb6\u4e13\u8457", "nodename": "\u6865\u672c\u5b87\u592a\u90ce \u8a70\u7881\u5c81\u65f6\u8bb0", "bookid": 201, "bookurl": "qiantian"}], "r": 2, "isguess": false, "qtypename": "\u6b7b\u6d3b\u9898", "myan": null, "attr_type": 0, "levelname": "1K+"}
