{"id": 188675, "qid": 188675, "publicid": 166052, "orgid": 0, "levelname": "9K+", "min_levelname": "12K", "max_levelname": "8K", "qtype": 5, "qtypename": "\u5b98\u5b50\u9898", "status": 2, "userid": 10768, "username": "\u94f6\u5188\u68cb\u9662", "hasdia": true, "dias": [], "attr_type": 0, "layoutnumber": 1, "issingle": true, "enable_answer": true, "sms_count": 0, "edit_count": 3, "islei": false, "leiid": 0, "taotaiid": 0, "bookinfos": [{"bookname": "\u300a\u56f4\u68cb\u6536\u5b98\u6280\u5de7\u300b", "bookid": 29924, "pinyin": "", "nodename": "\u5e38\u89c1\u5b98\u5b50\u76ee\u6570", "bookurl": 29924}], "specs": [], "taskresult": {"ok_nums": [30, 28, 44, 43, 93, 420, 776, 555, 535, 304, 312, 235, 189, 118, 114, 70, 64, 55, 37, 27, 22, 20, 16, 17, 8, 10, 9, 1, 2, 7], "fail_nums": [50, 46, 90, 136, 259, 984, 1219, 646, 477, 228, 145, 82, 61, 38, 22, 16, 16, 11, 6, 8, 1, 1, 1, 1, 2, 2, 1, 0, 0, 1], "ok_total": 4161, "fail_total": 4550}, "xuandians": [], "xds": [], "options": [], "vote": 4.8, "name": "\u53cc\u51486\u76ee", "title": "", "c": "amsTUV0QHRATV10QHRATVEIQHRATVEMQHRATV0AQHRATVUAQHRATVUEQHRATVl0QbBwRaRBaQxIdEhBVQBIdEhBaQBIdEhBUXhIdEhBVXhIdEhBbXhIdEhBXXxIdEhBUXBIdEhBWXBIdEhBRXBIdEhBWVhIdEhBUVhIdEhBUWxJsbw==", "r": 1, "prepos": [["oc", "oe", "pf", "qf", "re"], ["rh", "qg", "qh"]], "xv": 8, "points": [], "lu": 19, "blackfirst": true, "is_share": true, "answers": [{"id": 2883476, "st": 1, "ty": 1, "nu": 3, "username": "wx_494774711936", "userid": 1101087, "pts": [{"p": "pg", "c": ""}, {"p": "mb", "c": ""}, {"p": "ob", "c": ""}], "v": 0, "ok_count": 1, "change_count": 0, "bad_count": 0, "error_count": 0, "created": 1759664690}, {"id": 1006874, "st": 2, "ty": 1, "nu": 1, "username": "\u94f6\u5188\u68cb\u9662", "userid": 10863, "pts": [{"p": "nb", "c": ""}, {"p": "mb", "c": ""}, {"p": "ma", "c": ""}, {"p": "la", "c": ""}, {"p": "na", "c": ""}, {"p": "lb", "c": ""}], "v": 0, "ok_count": 11, "change_count": 0, "bad_count": 0, "error_count": 0, "created": 1581340429}], "ans_count": 2, "andata": {"0": {"subs": [1], "p": 0, "id": 0, "aids": [], "pt": "", "o": 0, "c": 0, "f": 0, "u": 0, "tip": ""}, "1": {"subs": [2], "p": 0, "id": 1, "aids": [1006874], "pt": "nb", "o": 1, "c": 0, "f": 0, "u": 0, "tip": ""}, "2": {"subs": [3], "p": 1, "id": 2, "aids": [1006874], "pt": "mb", "o": 1, "c": 0, "f": 0, "u": 0, "tip": ""}, "3": {"subs": [4], "p": 2, "id": 3, "aids": [1006874], "pt": "ma", "o": 1, "c": 0, "f": 0, "u": 0, "tip": ""}, "4": {"subs": [5], "p": 3, "id": 4, "aids": [1006874], "pt": "la", "o": 1, "c": 0, "f": 0, "u": 0, "tip": ""}, "5": {"subs": [6], "p": 4, "id": 5, "aids": [1006874], "pt": "na", "o": 1, "c": 0, "f": 0, "u": 0, "tip": ""}, "6": {"subs": [], "p": 5, "id": 6, "aids": [1006874], "pt": "lb", "o": 1, "c": 0, "f": 0, "u": 0, "tip": ""}}, "disuse": 1, "sx": 15, "sy": 11, "pos_x1": 4, "pos_x2": 18, "pos_y1": 0, "pos_y2": 10, "ineb": false, "extendwidth": 0, "signs": [], "luozis": [], "isguess": false, "objtype": "timu", "ru": 1, "content": "amsTXVcQHRATXVYQHRATQFcQHRATQ1QQHRATQFUQHRATQlQQHRATQVUQHRATXVEQbBwRaRBcVBIdEhBdVhIdEhBfUhIdEhBVVxIdEhBDVhIdEhBYVxIdEhBfVRIdEhBVVRIdEhBDWRIdEhBdVxIdEhBAWRIdEhBfVxIdEhBdWBJsbw==", "ok_answers": "amsTXFAQHRATX1AQHRATX1MQHRATXlMQHRATXFMQHRATXlAQbG0=", "change_answers": "am0=", "fail_answers": "am0=", "level": 38, "desc": "", "yes_count": 4161, "no_count": 4550, "pos": [], "attrtype": 0, "showrettip": false, "is_public": true, "inerror": false, "qshids": [], "myan": null, "hasbook": false, "hasspec": false, "myoper": {"mystar": false, "mytags": [], "tags": []}, "candisuseall": false, "userlevel": 0, "clicktime": 500, "xz": 0, "comments": [{"id": 1185976, "dou": 0, "doustatus": 0, "douname": "", "username": "w_33521535195129", "userid": 1181436, "headpath": "head/2022/11/3/1181436_8116_25_4.png", "updated": 1647661107, "showcontent": "10K"}, {"id": 1459014, "dou": 0, "doustatus": 0, "douname": "", "username": "\u683c\u5170\u83f2\u8fea", "userid": 1609657, "headpath": "head/2023/1/22/1609657_87428_52_45.png", "updated": 1674261537, "showcontent": "\u4e0d\u96be"}, {"id": 2115703, "dou": 0, "doustatus": 0, "douname": "", "username": "wx_35891139194316", "userid": 1838335, "headpath": "headicon_128.jpg", "updated": 1748177362, "showcontent": "\u53cc\u5148\u4ec0\u4e48\u610f\u601d\u554a\uff1f"}]}
